seolpyo_dstory/__init__.py
seolpyo_dstory/admin.py
seolpyo_dstory/apps.py
seolpyo_dstory/forms.py
seolpyo_dstory/processors.py
seolpyo_dstory/settings.py
seolpyo_dstory/tests.py
seolpyo_dstory/urls.py
seolpyo_dstory/migrations/0001_initial.py
seolpyo_dstory/migrations/__init__.py
seolpyo_dstory/models/__init__.py
seolpyo_dstory/models/postmodel.py
seolpyo_dstory/models/usermodel.py
seolpyo_dstory/templates/40x.html
seolpyo_dstory/templates/base.html
seolpyo_dstory/templates/seolpyo_dstory/detail.html
seolpyo_dstory/templates/seolpyo_dstory/form.html
seolpyo_dstory/templates/seolpyo_dstory/home.html
seolpyo_dstory/templates/seolpyo_dstory/list.html
seolpyo_dstory/templates/seolpyo_dstory/login.html
seolpyo_dstory/templates/seolpyo_dstory/signup.html
seolpyo_dstory/templates/seolpyo_dstory/sitemap.html
seolpyo_dstory/templates/seolpyo_dstory/summernote.html
seolpyo_dstory/utils/__init__.py
seolpyo_dstory/utils/request.py
seolpyo_dstory/utils/restore.py
seolpyo_dstory/views/__init__.py
seolpyo_dstory/views/detail.py
seolpyo_dstory/views/etc.py
seolpyo_dstory/views/feed.py
seolpyo_dstory/views/handler.py
seolpyo_dstory/views/list.py
seolpyo_dstory/views/post.py
seolpyo_dstory/views/user.py
seolpyo_dstory-0.0.23.dist-info/METADATA
seolpyo_dstory-0.0.23.dist-info/WHEEL
seolpyo_dstory-0.0.23.dist-info/top_level.txt
seolpyo_dstory-0.0.23.dist-info/RECORD
