Metadata-Version: 2.1
Name: seolpyo-dstory
Version: 0.0.23
Summary: 설표의 장고 디스토리, 티스토리 백업파일을 이용해 장고 사이트로 이사하기 위한 패키지입니다.
Author-email: white-seolpyo <white-seolpyo@naver.com>
Project-URL: Homepage, https://github.com/white-seolpyo/seolpyo_dstory
Project-URL: Issues, https://github.com/white-seolpyo/seolpyo_dstory/issues
Project-URL: Documentation, https://django.seolpyo.com/
Keywords: 티스토리,블로그,설표,하얀설표,이사,장고
Classifier: Environment :: Web Environment
Classifier: Intended Audience :: Developers
Classifier: License :: OSI Approved :: BSD License
Classifier: Operating System :: OS Independent
Classifier: Topic :: Internet :: WWW/HTTP
Classifier: Topic :: Internet :: WWW/HTTP :: Dynamic Content
Classifier: Framework :: Django
Classifier: Framework :: Django :: 5.1
Classifier: Programming Language :: Python
Classifier: Programming Language :: Python :: 3
Classifier: Programming Language :: Python :: 3 :: Only
Classifier: Programming Language :: Python :: 3.10
Requires-Python: >=3.10
Requires-Dist: tqdm >=4.66.5
Requires-Dist: beautifulsoup4 >=4.12.3
Requires-Dist: requests >=2.32.3
Requires-Dist: selenium >=4.25.0
Requires-Dist: django >=5.1.2
Requires-Dist: django-summernote >=0.8.20.0
